setup.py
rl_learn/__init__.py
rl_learn.egg-info/PKG-INFO
rl_learn.egg-info/SOURCES.txt
rl_learn.egg-info/dependency_links.txt
rl_learn.egg-info/not-zip-safe
rl_learn.egg-info/requires.txt
rl_learn.egg-info/top_level.txt
rl_learn/bandits/__init__.py
rl_learn/bandits/agents.py
rl_learn/bandits/environments.py
rl_learn/bandits/interaction.py